{"fantasy_content": {"xml:lang": "en-US", "yahoo:uri": "/fantasy/v2/league/380.l.155909/scoreboard;week=12", "league": [{"league_key": "380.l.155909", "league_id": "155909", "name": "League of Champions VIII", "url": "https://football.fantasysports.yahoo.com/f1/155909", "logo_url": "https://ct.yimg.com/cy/1806/29822858019_d317ec_192sq.jpg", "draft_status": "postdraft", "num_teams": 12, "edit_key": 4, "weekly_deadline": "", "league_update_timestamp": "1537942515", "scoring_type": "head", "league_type": "private", "renew": "371_391357", "renewed": "", "iris_group_chat_id": "VBEBZZAXKXTBDP5EUTPCU6ETXU", "allow_add_to_dl_extra_pos": 0, "is_pro_league": "0", "is_cash_league": "0", "current_week": 4, "start_week": "1", "start_date": "2018-09-06", "end_week": "16", "end_date": "2018-12-24", "game_code": "nfl", "season": "2018"}, {"scoreboard": {"week": "12", "0": {"matchups": {"0": {"matchup": {"week": "12", "week_start": "2018-11-20", "week_end": "2018-11-26", "status": "preevent", "is_playoffs": "0", "is_consolation": "0", "is_matchup_recap_available": 0, "0": {"teams": {"0": {"team": [[{"team_key": "380.l.155909.t.1"}, {"team_id": "1"}, {"name": "DCommish"}, [], {"url": "https://football.fantasysports.yahoo.com/f1/155909/1"}, {"team_logos": [{"team_logo": {"size": "large", "url": "https://ct.yimg.com/cy/4377/36896458745_c18f45_192sq.jpg?ct=fantasy?ct=fantasy"}}]}, [], {"waiver_priority": 10}, {"faab_balance": "172"}, {"number_of_moves": "6"}, {"number_of_trades": 0}, {"roster_adds": {"coverage_type": "week", "coverage_value": 4, "value": "1"}}, [], {"league_scoring_type": "head"}, [], [], {"has_draft_grade": 1, "draft_grade": "B", "draft_recap_url": "https://football.fantasysports.yahoo.com/f1/155909/1/draftrecap"}, [], [], {"managers": [{"manager": {"manager_id": "1", "nickname": "Daniel", "guid": "VJSO3RKXOKFJNFRY2BNC5ELQMA", "is_commissioner": "1", "email": "dconnoch@yahoo.com", "image_url": "https://ct.yimg.com/cy/1768/39361574426_98028a_64sq.jpg"}}]}], {"win_probability": 0.61, "team_points": {"coverage_type": "week", "week": "12", "total": "0.00"}, "team_projected_points": {"coverage_type": "week", "week": "12", "total": "106.61"}}]}, "1": {"team": [[{"team_key": "380.l.155909.t.2"}, {"team_id": "2"}, {"name": "Cat Dude"}, {"is_owned_by_current_login": 1}, {"url": "https://football.fantasysports.yahoo.com/f1/155909/2"}, {"team_logos": [{"team_logo": {"size": "large", "url": "https://ct.yimg.com/cy/1712/25024960220_b5650b59bd_192sq.jpg?ct=fantasy"}}]}, [], {"waiver_priority": 11}, {"faab_balance": "147"}, {"number_of_moves": "7"}, {"number_of_trades": 0}, {"roster_adds": {"coverage_type": "week", "coverage_value": 4, "value": "1"}}, [], {"league_scoring_type": "head"}, [], [], {"has_draft_grade": 1, "draft_grade": "B", "draft_recap_url": "https://football.fantasysports.yahoo.com/f1/155909/2/draftrecap"}, [], [], {"managers": [{"manager": {"manager_id": "2", "nickname": "Brian", "guid": "BEGKVJYC747IOARL4VAE4EJJ7I", "is_current_login": "1", "email": "brian.benbenek@gmail.com", "image_url": "https://ct.yimg.com/cy/1768/39361574426_98028a_64sq.jpg"}}]}], {"win_probability": 0.39, "team_points": {"coverage_type": "week", "week": "12", "total": "0.00"}, "team_projected_points": {"coverage_type": "week", "week": "12", "total": "95.04"}}]}, "count": 2}}}}, "1": {"matchup": {"week": "12", "week_start": "2018-11-20", "week_end": "2018-11-26", "status": "preevent", "is_playoffs": "0", "is_consolation": "0", "is_matchup_recap_available": 0, "0": {"teams": {"0": {"team": [[{"team_key": "380.l.155909.t.3"}, {"team_id": "3"}, {"name": "b o l o"}, [], {"url": "https://football.fantasysports.yahoo.com/f1/155909/3"}, {"team_logos": [{"team_logo": {"size": "large", "url": "https://ct.yimg.com/cy/1461/25318117705_7a43b0bd95_192sq.jpg?ct=fantasy"}}]}, [], {"waiver_priority": 2}, {"faab_balance": "175"}, {"number_of_moves": "3"}, {"number_of_trades": 0}, {"roster_adds": {"coverage_type": "week", "coverage_value": 4, "value": "1"}}, [], {"league_scoring_type": "head"}, [], [], {"has_draft_grade": 1, "draft_grade": "B-", "draft_recap_url": "https://football.fantasysports.yahoo.com/f1/155909/3/draftrecap"}, [], [], {"managers": [{"manager": {"manager_id": "3", "nickname": "Michael DeCrosta", "guid": "SV2UVTJ3X74UTTGTKL5ZLTNIEA", "email": "michael.decrosta@gmail.com", "image_url": "https://ct.yimg.com/cy/4688/37555871333_9757a2_64sq.jpg"}}]}], {"win_probability": 0.46, "team_points": {"coverage_type": "week", "week": "12", "total": "0.00"}, "team_projected_points": {"coverage_type": "week", "week": "12", "total": "101.94"}}]}, "1": {"team": [[{"team_key": "380.l.155909.t.11"}, {"team_id": "11"}, {"name": "Rolle That Blount"}, [], {"url": "https://football.fantasysports.yahoo.com/f1/155909/11"}, {"team_logos": [{"team_logo": {"size": "large", "url": "https://ct.yimg.com/cy/1634/36890369921_ec98bc_192sq.jpg?ct=fantasy"}}]}, [], {"waiver_priority": 7}, {"faab_balance": "200"}, {"number_of_moves": "1"}, {"number_of_trades": 0}, {"roster_adds": {"coverage_type": "week", "coverage_value": 4, "value": "0"}}, [], {"league_scoring_type": "head"}, [], [], {"has_draft_grade": 1, "draft_grade": "B", "draft_recap_url": "https://football.fantasysports.yahoo.com/f1/155909/11/draftrecap"}, [], [], {"managers": [{"manager": {"manager_id": "11", "nickname": "Tim Bacak", "guid": "XS6ZBJHDVPP4BSJEN2RMRAGRA4", "email": "timothy.bacak@temple.edu", "image_url": "https://ct.yimg.com/cy/4638/24296693377_2b058d_64sq.jpg"}}]}], {"win_probability": 0.54, "team_points": {"coverage_type": "week", "week": "12", "total": "0.00"}, "team_projected_points": {"coverage_type": "week", "week": "12", "total": "105.99"}}]}, "count": 2}}}}, "2": {"matchup": {"week": "12", "week_start": "2018-11-20", "week_end": "2018-11-26", "status": "preevent", "is_playoffs": "0", "is_consolation": "0", "is_matchup_recap_available": 0, "0": {"teams": {"0": {"team": [[{"team_key": "380.l.155909.t.4"}, {"team_id": "4"}, {"name": "MistyMountainHopkins"}, [], {"url": "https://football.fantasysports.yahoo.com/f1/155909/4"}, {"team_logos": [{"team_logo": {"size": "large", "url": "https://ct.yimg.com/cy/1793/43584422345_77f17e_192sq.jpg?ct=fantasy"}}]}, [], {"waiver_priority": 5}, {"faab_balance": "140"}, {"number_of_moves": "4"}, {"number_of_trades": 0}, {"roster_adds": {"coverage_type": "week", "coverage_value": 4, "value": "0"}}, [], {"league_scoring_type": "head"}, [], [], {"has_draft_grade": 1, "draft_grade": "C", "draft_recap_url": "https://football.fantasysports.yahoo.com/f1/155909/4/draftrecap"}, [], [], {"managers": [{"manager": {"manager_id": "4", "nickname": "Erik", "guid": "YJ3NLIYDIVG4SP4PHMWKH4M6QE", "email": "emk544@gmail.com", "image_url": "https://ct.yimg.com/cy/1768/39361574426_98028a_64sq.jpg"}}]}], {"win_probability": 0.33, "team_points": {"coverage_type": "week", "week": "12", "total": "0.00"}, "team_projected_points": {"coverage_type": "week", "week": "12", "total": "99.98"}}]}, "1": {"team": [[{"team_key": "380.l.155909.t.10"}, {"team_id": "10"}, {"name": "ACROWLeftoftheMurder"}, [], {"url": "https://football.fantasysports.yahoo.com/f1/155909/10"}, {"team_logos": [{"team_logo": {"size": "large", "url": "https://ct.yimg.com/cy/1556/24671187724_e0327cbdf1_192sq.jpg?ct=fantasy"}}]}, [], {"waiver_priority": 4}, {"faab_balance": "198"}, {"number_of_moves": "2"}, {"number_of_trades": 0}, {"roster_adds": {"coverage_type": "week", "coverage_value": 4, "value": "1"}}, [], {"league_scoring_type": "head"}, [], [], {"has_draft_grade": 1, "draft_grade": "B", "draft_recap_url": "https://football.fantasysports.yahoo.com/f1/155909/10/draftrecap"}, [], [], {"managers": [{"manager": {"manager_id": "10", "nickname": "Brian Z", "guid": "SPYDKIRBQCKVKERCP3YGUZUVP4", "email": "bzakeski@gmail.com", "image_url": "https://ct.yimg.com/cy/4524/37471775553_4f0aee_64sq.jpg"}}]}], {"win_probability": 0.67, "team_points": {"coverage_type": "week", "week": "12", "total": "0.00"}, "team_projected_points": {"coverage_type": "week", "week": "12", "total": "118.87"}}]}, "count": 2}}}}, "3": {"matchup": {"week": "12", "week_start": "2018-11-20", "week_end": "2018-11-26", "status": "preevent", "is_playoffs": "0", "is_consolation": "0", "is_matchup_recap_available": 0, "0": {"teams": {"0": {"team": [[{"team_key": "380.l.155909.t.5"}, {"team_id": "5"}, {"name": "Chudley Cannons"}, [], {"url": "https://football.fantasysports.yahoo.com/f1/155909/5"}, {"team_logos": [{"team_logo": {"size": "large", "url": "https://ct.yimg.com/cy/1796/43482675655_217351_192sq.jpg?ct=fantasy?ct=fantasy"}}]}, [], {"waiver_priority": 6}, {"faab_balance": "191"}, {"number_of_moves": "2"}, {"number_of_trades": 0}, {"roster_adds": {"coverage_type": "week", "coverage_value": 4, "value": "1"}}, [], {"league_scoring_type": "head"}, [], [], {"has_draft_grade": 1, "draft_grade": "C", "draft_recap_url": "https://football.fantasysports.yahoo.com/f1/155909/5/draftrecap"}, [], [], {"managers": [{"manager": {"manager_id": "5", "nickname": "Zack B", "guid": "YCPIPVO3YK2H6YQUHHDJ4OMNII", "email": "zack.biro@gmail.com", "image_url": "https://ct.yimg.com/cy/4565/39018940696_69862a_64sq.jpg"}}]}], {"win_probability": 0.32, "team_points": {"coverage_type": "week", "week": "12", "total": "0.00"}, "team_projected_points": {"coverage_type": "week", "week": "12", "total": "67.31"}}]}, "1": {"team": [[{"team_key": "380.l.155909.t.9"}, {"team_id": "9"}, {"name": "Legion of Vroom"}, [], {"url": "https://football.fantasysports.yahoo.com/f1/155909/9"}, {"team_logos": [{"team_logo": {"size": "large", "url": "https://ct.yimg.com/cy/4409/36225559343_720f7f_192sq.jpg?ct=fantasy"}}]}, [], {"waiver_priority": 3}, {"faab_balance": "157"}, {"number_of_moves": "10"}, {"number_of_trades": 0}, {"roster_adds": {"coverage_type": "week", "coverage_value": 4, "value": "0"}}, [], {"league_scoring_type": "head"}, [], [], {"has_draft_grade": 1, "draft_grade": "C", "draft_recap_url": "https://football.fantasysports.yahoo.com/f1/155909/9/draftrecap"}, [], [], {"managers": [{"manager": {"manager_id": "9", "nickname": "Andrew", "guid": "6LQOKTMZXU4TC6F6RQH6DLXWX4", "email": "astone171@yahoo.com", "image_url": "https://ct.yimg.com/cy/1768/39361574426_98028a_64sq.jpg"}}]}], {"win_probability": 0.68, "team_points": {"coverage_type": "week", "week": "12", "total": "0.00"}, "team_projected_points": {"coverage_type": "week", "week": "12", "total": "82.96"}}]}, "count": 2}}}}, "4": {"matchup": {"week": "12", "week_start": "2018-11-20", "week_end": "2018-11-26", "status": "preevent", "is_playoffs": "0", "is_consolation": "0", "is_matchup_recap_available": 0, "0": {"teams": {"0": {"team": [[{"team_key": "380.l.155909.t.6"}, {"team_id": "6"}, {"name": "16 Angry Democrats"}, [], {"url": "https://football.fantasysports.yahoo.com/f1/155909/6"}, {"team_logos": [{"team_logo": {"size": "large", "url": "https://s.yimg.com/cv/api/default/20180727/nfl_08.png"}}]}, [], {"waiver_priority": 12}, {"faab_balance": "131"}, {"number_of_moves": "7"}, {"number_of_trades": 0}, {"roster_adds": {"coverage_type": "week", "coverage_value": 4, "value": "1"}}, [], {"league_scoring_type": "head"}, [], [], {"has_draft_grade": 1, "draft_grade": "A-", "draft_recap_url": "https://football.fantasysports.yahoo.com/f1/155909/6/draftrecap"}, [], [], {"managers": [{"manager": {"manager_id": "6", "nickname": "Eds", "guid": "SZQONSMRFV3LW6B5MNZJEXRGZA", "email": "stevenet@bc.edu", "image_url": "https://ct.yimg.com/cy/1768/39361574426_98028a_64sq.jpg"}}]}], {"win_probability": 0.48, "team_points": {"coverage_type": "week", "week": "12", "total": "0.00"}, "team_projected_points": {"coverage_type": "week", "week": "12", "total": "98.89"}}]}, "1": {"team": [[{"team_key": "380.l.155909.t.8"}, {"team_id": "8"}, {"name": "I hateyou ToddGurley"}, [], {"url": "https://football.fantasysports.yahoo.com/f1/155909/8"}, {"team_logos": [{"team_logo": {"size": "large", "url": "https://s.yimg.com/cv/api/default/20180727/nfl_04.png"}}]}, [], {"waiver_priority": 1}, {"faab_balance": "180"}, {"number_of_moves": "2"}, {"number_of_trades": 0}, {"roster_adds": {"coverage_type": "week", "coverage_value": 4, "value": "0"}}, [], {"league_scoring_type": "head"}, [], [], {"has_draft_grade": 1, "draft_grade": "B", "draft_recap_url": "https://football.fantasysports.yahoo.com/f1/155909/8/draftrecap"}, [], [], {"managers": [{"manager": {"manager_id": "8", "nickname": "Stephen", "guid": "HVQYJGNFC44FS2FSNY4SYQQ374", "email": "sheaney72@yahoo.com", "image_url": "https://ct.yimg.com/cy/1768/39361574426_98028a_64sq.jpg"}}]}], {"win_probability": 0.52, "team_points": {"coverage_type": "week", "week": "12", "total": "0.00"}, "team_projected_points": {"coverage_type": "week", "week": "12", "total": "100.55"}}]}, "count": 2}}}}, "5": {"matchup": {"week": "12", "week_start": "2018-11-20", "week_end": "2018-11-26", "status": "preevent", "is_playoffs": "0", "is_consolation": "0", "is_matchup_recap_available": 0, "0": {"teams": {"0": {"team": [[{"team_key": "380.l.155909.t.7"}, {"team_id": "7"}, {"name": "Boomin Brown Reunion"}, [], {"url": "https://football.fantasysports.yahoo.com/f1/155909/7"}, {"team_logos": [{"team_logo": {"size": "large", "url": "https://ct.yimg.com/cy/1665/24669900694_fac82f8b08_192sq.jpg?ct=fantasy"}}]}, [], {"waiver_priority": 8}, {"faab_balance": "200"}, {"number_of_moves": "4"}, {"number_of_trades": 0}, {"roster_adds": {"coverage_type": "week", "coverage_value": 4, "value": "0"}}, [], {"league_scoring_type": "head"}, [], [], {"has_draft_grade": 1, "draft_grade": "C+", "draft_recap_url": "https://football.fantasysports.yahoo.com/f1/155909/7/draftrecap"}, [], [], {"managers": [{"manager": {"manager_id": "7", "nickname": "Kereeti", "guid": "W7JSNZCWIFODIGL6MDNVTNYPD4", "email": "kereetip@gmail.com", "image_url": "https://ct.yimg.com/cy/1768/39361574426_98028a_64sq.jpg"}}]}], {"win_probability": 0.33, "team_points": {"coverage_type": "week", "week": "12", "total": "0.00"}, "team_projected_points": {"coverage_type": "week", "week": "12", "total": "92.67"}}]}, "1": {"team": [[{"team_key": "380.l.155909.t.12"}, {"team_id": "12"}, {"name": "No CAM Rocket"}, [], {"url": "https://football.fantasysports.yahoo.com/f1/155909/12"}, {"team_logos": [{"team_logo": {"size": "large", "url": "https://ct.yimg.com/cy/1697/25342603795_44cc525bd7_192sq.jpg?ct=fantasy"}}]}, [], {"waiver_priority": 9}, {"faab_balance": "175"}, {"number_of_moves": "4"}, {"number_of_trades": 0}, {"roster_adds": {"coverage_type": "week", "coverage_value": 4, "value": "2"}}, [], {"league_scoring_type": "head"}, [], [], {"has_draft_grade": 1, "draft_grade": "C", "draft_recap_url": "https://football.fantasysports.yahoo.com/f1/155909/12/draftrecap"}, [], [], {"managers": [{"manager": {"manager_id": "12", "nickname": "Dan", "guid": "YH6JAGQFMPCDUIZR2S5AAO3YSQ", "email": "denialtwister31@gmail.com", "image_url": "https://ct.yimg.com/cy/1768/39361574426_98028a_64sq.jpg"}}]}], {"win_probability": 0.67, "team_points": {"coverage_type": "week", "week": "12", "total": "0.00"}, "team_projected_points": {"coverage_type": "week", "week": "12", "total": "110.29"}}]}, "count": 2}}}}, "count": 6}}}}], "time": "186.91897392273ms", "copyright": "Data provided by Yahoo! and STATS, LLC", "refresh_rate": "120"}}